ufs2arco/__init__.py
ufs2arco/cice6dataset.py
ufs2arco/cli.py
ufs2arco/datamover.py
ufs2arco/driver.py
ufs2arco/fv3dataset.py
ufs2arco/layers2pressure.py
ufs2arco/log.py
ufs2arco/mom6dataset.py
ufs2arco/mpi.py
ufs2arco/multidriver.py
ufs2arco/replay_vertical_levels.yaml
ufs2arco/timer.py
ufs2arco/ufsdataset.py
ufs2arco/utils.py
ufs2arco/regrid/__init__.py
ufs2arco/regrid/cice6regridder.py
ufs2arco/regrid/gaussian_grid.py
ufs2arco/regrid/mom6regridder.py
ufs2arco/regrid/ufsregridder.py
ufs2arco/sources/__init__.py
ufs2arco/sources/aws_aorc.py
ufs2arco/sources/aws_gefs_archive.py
ufs2arco/sources/aws_hrrr_archive.py
ufs2arco/sources/base.py
ufs2arco/sources/cloud_zarr.py
ufs2arco/sources/gcs_era5_1degree.py
ufs2arco/sources/gcs_replay_atmosphere.py
ufs2arco/sources/gfs_archive.py
ufs2arco/sources/noaa_grib_forecast.py
ufs2arco/sources/reference.gefs.yaml
ufs2arco/sources/reference.gfs.yaml
ufs2arco/sources/reference.hrrr.yaml
ufs2arco/targets/__init__.py
ufs2arco/targets/anemoi.py
ufs2arco/targets/base.py
ufs2arco/targets/forcings.py
ufs2arco/transforms/__init__.py
ufs2arco/transforms/horizontal_regrid.py
ufs2arco/transforms/mappings.py
ufs2arco/transforms/rotate_vectors.py
ufs2arco/transforms/transformer.py
ufs2arco/transforms/vertical_regrid.py
ufs2arco-0.18.0.dist-info/licenses/LICENSE
ufs2arco-0.18.0.dist-info/METADATA
ufs2arco-0.18.0.dist-info/WHEEL
ufs2arco-0.18.0.dist-info/entry_points.txt
ufs2arco-0.18.0.dist-info/top_level.txt
ufs2arco-0.18.0.dist-info/RECORD
