Metadata-Version: 2.4
Name: ufs2arco
Version: 0.18.0
Summary: Tools for converting Unified Forecast System (UFS) output to Analysis Ready, Cloud Optimized (ARCO) format
Author-email: Timothy Smith <tim.smith@noaa.gov>
Project-URL: source, https://github.com/NOAA-PSL/ufs2arco
Project-URL: documentation, https://ufs2arco.readthedocs.io/en/latest/
Requires-Python: >=3.10
License-File: LICENSE
Requires-Dist: numpy<2.3
Requires-Dist: xarray
Requires-Dist: cf_xarray
Requires-Dist: cftime
Requires-Dist: netCDF4
Requires-Dist: h5netcdf
Requires-Dist: zarr<3
Requires-Dist: cfgrib
Requires-Dist: bottleneck
Requires-Dist: flox
Requires-Dist: dask[complete]
Requires-Dist: fsspec
Requires-Dist: s3fs
Requires-Dist: gcsfs>=2025.10.0
Provides-Extra: documentation
Requires-Dist: jupyter; extra == "documentation"
Requires-Dist: nbsphinx; extra == "documentation"
Requires-Dist: sphinx-book-theme; extra == "documentation"
Requires-Dist: matplotlib; extra == "documentation"
Provides-Extra: regrid
Requires-Dist: xesmf; extra == "regrid"
Provides-Extra: mpi
Requires-Dist: mpi4py; extra == "mpi"
Provides-Extra: dev
Requires-Dist: setuptools_scm>=8; extra == "dev"
Requires-Dist: pytest; extra == "dev"
Requires-Dist: pytest-dependency; extra == "dev"
Requires-Dist: coverage; extra == "dev"
Dynamic: license-file
